{
	"Name": "FACA Cape Town FIR v2",
	"Composites": [
		{
			"Name": "Cape Town Intl",
			"Identifier": "FACT",
			"Contractions": [
				{
					"String": "RNAV",
					"Spoken": "ARE-NAV"
				},
				{
					"String": "CAVOK",
					"Spoken": "CAV-OH-KAY"
				},
				{
					"String": "RNP",
					"Spoken": "ARE-ENN-PEE"
				}
			],
			"AtisFrequency": 27000,
			"ObservationTime": {
				"Enabled": false,
				"Time": 0
			},
			"MagneticVariation": {
				"Enabled": false,
				"MagneticDegrees": 0
			},
			"AtisVoice": {
				"UseTextToSpeech": true,
				"Voice": "Default"
			},
			"IDSEndpoint": "",
			"Presets": [
				{
					"Name": "RWY 01",
					"AirportConditions": "RUNWAY 01 IN USE. EXPECT RNAV APPROACH. ",
					"Notams": null,
					"ArbitraryText": null,
					"Template": "[FACILITY] ATIS INFORMATION [ATIS_CODE]. [OBS_TIME]. [FULL_WX_STRING]. [ARPT_COND]. [NOTAMS]. [TL]."
				},
				{
					"Name": "RWY 19",
					"AirportConditions": "RUNWAY 19 IN USE. EXPECT ILS APPROACH.",
					"Notams": null,
					"ArbitraryText": null,
					"Template": "[FACILITY] ATIS INFORMATION [ATIS_CODE]. [OBS_TIME]. [FULL_WX_STRING]. [ARPT_COND]. [NOTAMS]. [TL]."
				}
			],
			"AirportConditionDefinitions": [],
			"NotamDefinitions": [],
			"TransitionLevels": [
				{
					"Low": 1047,
					"High": 1099,
					"Altitude": 75
				},
				{
					"Low": 1030,
					"High": 1046,
					"Altitude": 80
				},
				{
					"Low": 1014,
					"High": 1029,
					"Altitude": 85
				},
				{
					"Low": 997,
					"High": 1013,
					"Altitude": 90
				},
				{
					"Low": 980,
					"High": 996,
					"Altitude": 95
				},
				{
					"Low": 963,
					"High": 979,
					"Altitude": 100
				},
				{
					"Low": 946,
					"High": 962,
					"Altitude": 105
				}
			],
			"UseFaaFormat": false,
			"UseNotamPrefix": false,
			"UseTransitionLevelPrefix": true,
			"UseMetricUnits": false,
			"UseSurfaceWindPrefix": true,
			"UseVisibilitySuffix": true,
			"UseDecimalTerminology": true,
			"UseTemperaturePlusPrefix": false,
			"UseZuluTimeSuffix": true
		},
		{
			"Name": "East London King Phalo",
			"Identifier": "FAEL",
			"Contractions": [
				{
					"String": "RNAV",
					"Spoken": "ARE-NAV"
				},
				{
					"String": "CAVOK",
					"Spoken": "CAV-OH-KAY"
				},
				{
					"String": "RNP",
					"Spoken": "ARE-ENN-PEE"
				}
			],
			"AtisFrequency": 26650,
			"ObservationTime": {
				"Enabled": false,
				"Time": 0
			},
			"MagneticVariation": {
				"Enabled": false,
				"MagneticDegrees": 0
			},
			"AtisVoice": {
				"UseTextToSpeech": true,
				"Voice": "Default"
			},
			"IDSEndpoint": "",
			"Presets": [
				{
					"Name": "RWY 11",
					"AirportConditions": "RUNWAY 11 IN USE. EXPECT ILS APPROACH. ",
					"Notams": null,
					"ArbitraryText": null,
					"Template": "[FACILITY] ATIS INFORMATION [ATIS_CODE]. [OBS_TIME]. [FULL_WX_STRING]. [ARPT_COND]. [NOTAMS]. [TL]."
				},
				{
					"Name": "RWY 29",
					"AirportConditions": "RUNWAY 29 IN USE. EXPECT ILS APPROACH.",
					"Notams": null,
					"ArbitraryText": null,
					"Template": "[FACILITY] ATIS INFORMATION [ATIS_CODE]. [OBS_TIME]. [FULL_WX_STRING]. [ARPT_COND]. [NOTAMS]. [TL]."
				}
			],
			"AirportConditionDefinitions": [],
			"NotamDefinitions": [],
			"TransitionLevels": [
				{
					"Low": 1047,
					"High": 1099,
					"Altitude": 70
				},
				{
					"Low": 1030,
					"High": 1046,
					"Altitude": 75
				},
				{
					"Low": 1014,
					"High": 1029,
					"Altitude": 80
				},
				{
					"Low": 997,
					"High": 1013,
					"Altitude": 85
				},
				{
					"Low": 980,
					"High": 996,
					"Altitude": 90
				},
				{
					"Low": 963,
					"High": 979,
					"Altitude": 95
				},
				{
					"Low": 946,
					"High": 962,
					"Altitude": 100
				}
			],
			"UseFaaFormat": false,
			"UseNotamPrefix": false,
			"UseTransitionLevelPrefix": true,
			"UseMetricUnits": false,
			"UseSurfaceWindPrefix": true,
			"UseVisibilitySuffix": true,
			"UseDecimalTerminology": true,
			"UseTemperaturePlusPrefix": false,
			"UseZuluTimeSuffix": true
		},
		{
			"Name": "George",
			"Identifier": "FAGG",
			"Contractions": [
				{
					"String": "RNAV",
					"Spoken": "ARE-NAV"
				},
				{
					"String": "CAVOK",
					"Spoken": "CAV-OH-KAY"
				},
				{
					"String": "RNP",
					"Spoken": "ARE-ENN-PEE"
				}
			],
			"AtisFrequency": 26225,
			"ObservationTime": {
				"Enabled": false,
				"Time": 0
			},
			"MagneticVariation": {
				"Enabled": false,
				"MagneticDegrees": 0
			},
			"AtisVoice": {
				"UseTextToSpeech": true,
				"Voice": "Default"
			},
			"IDSEndpoint": "",
			"Presets": [
				{
					"Name": "RWY 11",
					"AirportConditions": "RUNWAY 11 IN USE. EXPECT ILS APPROACH. ",
					"Notams": null,
					"ArbitraryText": null,
					"Template": "[FACILITY] ATIS INFORMATION [ATIS_CODE]. [OBS_TIME]. [FULL_WX_STRING]. [ARPT_COND]. [NOTAMS]. [TL]."
				},
				{
					"Name": "RWY 29",
					"AirportConditions": "RUNWAY 29 IN USE. EXPECT ILS APPROACH.",
					"Notams": null,
					"ArbitraryText": null,
					"Template": "[FACILITY] ATIS INFORMATION [ATIS_CODE]. [OBS_TIME]. [FULL_WX_STRING]. [ARPT_COND]. [NOTAMS]. [TL]."
				}
			],
			"AirportConditionDefinitions": [],
			"NotamDefinitions": [],
			"TransitionLevels": [
				{
					"Low": 1047,
					"High": 1099,
					"Altitude": 80
				},
				{
					"Low": 1030,
					"High": 1046,
					"Altitude": 85
				},
				{
					"Low": 1014,
					"High": 1029,
					"Altitude": 90
				},
				{
					"Low": 997,
					"High": 1013,
					"Altitude": 95
				},
				{
					"Low": 980,
					"High": 996,
					"Altitude": 100
				},
				{
					"Low": 963,
					"High": 979,
					"Altitude": 105
				},
				{
					"Low": 946,
					"High": 962,
					"Altitude": 110
				}
			],
			"UseFaaFormat": false,
			"UseNotamPrefix": false,
			"UseTransitionLevelPrefix": true,
			"UseMetricUnits": false,
			"UseSurfaceWindPrefix": true,
			"UseVisibilitySuffix": true,
			"UseDecimalTerminology": true,
			"UseTemperaturePlusPrefix": false,
			"UseZuluTimeSuffix": true
		},
		{
			"Name": "Port Elizabeth Intl",
			"Identifier": "FAPE",
			"Contractions": [
				{
					"String": "RNAV",
					"Spoken": "ARE-NAV"
				},
				{
					"String": "CAVOK",
					"Spoken": "CAV-OH-KAY"
				},
				{
					"String": "RNP",
					"Spoken": "ARE-ENN-PEE"
				}
			],
			"AtisFrequency": 26800,
			"ObservationTime": {
				"Enabled": false,
				"Time": 0
			},
			"MagneticVariation": {
				"Enabled": false,
				"MagneticDegrees": 0
			},
			"AtisVoice": {
				"UseTextToSpeech": true,
				"Voice": "Default"
			},
			"IDSEndpoint": "",
			"Presets": [
				{
					"Name": "RWY 08",
					"AirportConditions": "RUNWAY 08 IN USE. EXPECT ILS APPROACH.",
					"Notams": null,
					"ArbitraryText": null,
					"Template": "[FACILITY] ATIS INFORMATION [ATIS_CODE]. [OBS_TIME]. [FULL_WX_STRING]. [ARPT_COND]. [NOTAMS]. [TL]."
				},
				{
					"Name": "RWY 26",
					"AirportConditions": "RUNWAY 26 IN USE. EXPECT ILS APPROACH.",
					"Notams": null,
					"ArbitraryText": null,
					"Template": "[FACILITY] ATIS INFORMATION [ATIS_CODE]. [OBS_TIME]. [FULL_WX_STRING]. [ARPT_COND]. [NOTAMS]. [TL]."
				}
			],
			"AirportConditionDefinitions": [],
			"NotamDefinitions": [],
			"TransitionLevels": [
				{
					"Low": 1047,
					"High": 1099,
					"Altitude": 55
				},
				{
					"Low": 1030,
					"High": 1046,
					"Altitude": 60
				},
				{
					"Low": 1014,
					"High": 1029,
					"Altitude": 65
				},
				{
					"Low": 997,
					"High": 1013,
					"Altitude": 70
				},
				{
					"Low": 980,
					"High": 996,
					"Altitude": 75
				},
				{
					"Low": 963,
					"High": 979,
					"Altitude": 80
				},
				{
					"Low": 946,
					"High": 962,
					"Altitude": 85
				}
			],
			"UseFaaFormat": false,
			"UseNotamPrefix": false,
			"UseTransitionLevelPrefix": true,
			"UseMetricUnits": false,
			"UseSurfaceWindPrefix": true,
			"UseVisibilitySuffix": true,
			"UseDecimalTerminology": true,
			"UseTemperaturePlusPrefix": false,
			"UseZuluTimeSuffix": true
		}
	]
}
